{
  "activity_id": 23373152386,
  "v": 3,
  "series": [
    {
      "t": 0,
      "hr": 74,
      "pace": null,
      "cad": null,
      "stride": null
    },
    {
      "t": 23,
      "hr": 90,
      "pace": null,
      "cad": null,
      "stride": null
    },
    {
      "t": 49,
      "hr": 80,
      "pace": null,
      "cad": null,
      "stride": null
    },
    {
      "t": 68,
      "hr": 51,
      "pace": null,
      "cad": null,
      "stride": null
    },
    {
      "t": 81,
      "hr": 54,
      "pace": null,
      "cad": null,
      "stride": null
    },
    {
      "t": 104,
      "hr": 49,
      "pace": null,
      "cad": null,
      "stride": null
    },
    {
      "t": 127,
      "hr": 61,
      "pace": null,
      "cad": null,
      "stride": null
    },
    {
      "t": 153,
      "hr": 108,
      "pace": null,
      "cad": null,
      "stride": null
    },
    {
      "t": 177,
      "hr": 123,
      "pace": null,
      "cad": null,
      "stride": null
    },
    {
      "t": 221,
      "hr": 131,
      "pace": null,
      "cad": null,
      "stride": null
    },
    {
      "t": 249,
      "hr": 130,
      "pace": null,
      "cad": null,
      "stride": null
    },
    {
      "t": 286,
      "hr": 132,
      "pace": null,
      "cad": null,
      "stride": null
    },
    {
      "t": 308,
      "hr": 128,
      "pace": null,
      "cad": null,
      "stride": null
    },
    {
      "t": 346,
      "hr": 130,
      "pace": null,
      "cad": null,
      "stride": null
    },
    {
      "t": 379,
      "hr": 136,
      "pace": null,
      "cad": null,
      "stride": null
    },
    {
      "t": 408,
      "hr": 150,
      "pace": null,
      "cad": null,
      "stride": null
    },
    {
      "t": 427,
      "hr": 148,
      "pace": null,
      "cad": null,
      "stride": null
    },
    {
      "t": 450,
      "hr": 133,
      "pace": null,
      "cad": null,
      "stride": null
    },
    {
      "t": 472,
      "hr": 142,
      "pace": null,
      "cad": null,
      "stride": null
    },
    {
      "t": 489,
      "hr": 136,
      "pace": null,
      "cad": null,
      "stride": null
    },
    {
      "t": 525,
      "hr": 131,
      "pace": null,
      "cad": null,
      "stride": null
    },
    {
      "t": 556,
      "hr": 141,
      "pace": null,
      "cad": null,
      "stride": null
    },
    {
      "t": 594,
      "hr": 144,
      "pace": null,
      "cad": null,
      "stride": null
    },
    {
      "t": 631,
      "hr": 137,
      "pace": null,
      "cad": null,
      "stride": null
    },
    {
      "t": 666,
      "hr": 135,
      "pace": null,
      "cad": null,
      "stride": null
    },
    {
      "t": 707,
      "hr": 141,
      "pace": null,
      "cad": null,
      "stride": null
    },
    {
      "t": 741,
      "hr": 129,
      "pace": null,
      "cad": null,
      "stride": null
    },
    {
      "t": 765,
      "hr": 121,
      "pace": null,
      "cad": null,
      "stride": null
    },
    {
      "t": 793,
      "hr": 129,
      "pace": null,
      "cad": null,
      "stride": null
    },
    {
      "t": 819,
      "hr": 144,
      "pace": null,
      "cad": null,
      "stride": null
    },
    {
      "t": 848,
      "hr": 132,
      "pace": null,
      "cad": null,
      "stride": null
    },
    {
      "t": 869,
      "hr": 126,
      "pace": null,
      "cad": null,
      "stride": null
    },
    {
      "t": 894,
      "hr": 145,
      "pace": null,
      "cad": null,
      "stride": null
    },
    {
      "t": 918,
      "hr": 128,
      "pace": null,
      "cad": null,
      "stride": null
    },
    {
      "t": 944,
      "hr": 140,
      "pace": null,
      "cad": null,
      "stride": null
    },
    {
      "t": 974,
      "hr": 148,
      "pace": null,
      "cad": null,
      "stride": null
    },
    {
      "t": 1004,
      "hr": 136,
      "pace": null,
      "cad": null,
      "stride": null
    },
    {
      "t": 1029,
      "hr": 140,
      "pace": null,
      "cad": null,
      "stride": null
    },
    {
      "t": 1059,
      "hr": 154,
      "pace": null,
      "cad": null,
      "stride": null
    },
    {
      "t": 1084,
      "hr": 154,
      "pace": null,
      "cad": null,
      "stride": null
    },
    {
      "t": 1113,
      "hr": 143,
      "pace": null,
      "cad": null,
      "stride": null
    },
    {
      "t": 1145,
      "hr": 142,
      "pace": null,
      "cad": null,
      "stride": null
    },
    {
      "t": 1168,
      "hr": 143,
      "pace": null,
      "cad": null,
      "stride": null
    },
    {
      "t": 1190,
      "hr": 145,
      "pace": null,
      "cad": null,
      "stride": null
    },
    {
      "t": 1228,
      "hr": 128,
      "pace": null,
      "cad": null,
      "stride": null
    },
    {
      "t": 1251,
      "hr": 130,
      "pace": null,
      "cad": null,
      "stride": null
    },
    {
      "t": 1272,
      "hr": 128,
      "pace": null,
      "cad": null,
      "stride": null
    },
    {
      "t": 1305,
      "hr": 127,
      "pace": null,
      "cad": null,
      "stride": null
    },
    {
      "t": 1339,
      "hr": 119,
      "pace": null,
      "cad": null,
      "stride": null
    },
    {
      "t": 1363,
      "hr": 119,
      "pace": null,
      "cad": null,
      "stride": null
    },
    {
      "t": 1380,
      "hr": 99,
      "pace": null,
      "cad": null,
      "stride": null
    },
    {
      "t": 1396,
      "hr": 114,
      "pace": null,
      "cad": null,
      "stride": null
    },
    {
      "t": 1427,
      "hr": 116,
      "pace": null,
      "cad": null,
      "stride": null
    },
    {
      "t": 1454,
      "hr": 117,
      "pace": null,
      "cad": null,
      "stride": null
    },
    {
      "t": 1484,
      "hr": 136,
      "pace": null,
      "cad": null,
      "stride": null
    },
    {
      "t": 1519,
      "hr": 140,
      "pace": null,
      "cad": null,
      "stride": null
    },
    {
      "t": 1545,
      "hr": 139,
      "pace": null,
      "cad": null,
      "stride": null
    },
    {
      "t": 1576,
      "hr": 145,
      "pace": null,
      "cad": null,
      "stride": null
    },
    {
      "t": 1610,
      "hr": 130,
      "pace": null,
      "cad": null,
      "stride": null
    },
    {
      "t": 1635,
      "hr": 138,
      "pace": null,
      "cad": null,
      "stride": null
    },
    {
      "t": 1653,
      "hr": 136,
      "pace": null,
      "cad": null,
      "stride": null
    },
    {
      "t": 1685,
      "hr": 144,
      "pace": null,
      "cad": null,
      "stride": null
    },
    {
      "t": 1716,
      "hr": 136,
      "pace": null,
      "cad": null,
      "stride": null
    },
    {
      "t": 1747,
      "hr": 143,
      "pace": null,
      "cad": null,
      "stride": null
    },
    {
      "t": 1785,
      "hr": 131,
      "pace": null,
      "cad": null,
      "stride": null
    },
    {
      "t": 1815,
      "hr": 141,
      "pace": null,
      "cad": null,
      "stride": null
    },
    {
      "t": 1846,
      "hr": 142,
      "pace": null,
      "cad": null,
      "stride": null
    },
    {
      "t": 1879,
      "hr": 153,
      "pace": null,
      "cad": null,
      "stride": null
    },
    {
      "t": 1899,
      "hr": 135,
      "pace": null,
      "cad": null,
      "stride": null
    },
    {
      "t": 1923,
      "hr": 144,
      "pace": null,
      "cad": null,
      "stride": null
    },
    {
      "t": 1950,
      "hr": 146,
      "pace": null,
      "cad": null,
      "stride": null
    },
    {
      "t": 1968,
      "hr": 129,
      "pace": null,
      "cad": null,
      "stride": null
    },
    {
      "t": 2000,
      "hr": 137,
      "pace": null,
      "cad": null,
      "stride": null
    },
    {
      "t": 2032,
      "hr": 139,
      "pace": null,
      "cad": null,
      "stride": null
    },
    {
      "t": 2053,
      "hr": 141,
      "pace": null,
      "cad": null,
      "stride": null
    },
    {
      "t": 2087,
      "hr": 140,
      "pace": null,
      "cad": null,
      "stride": null
    },
    {
      "t": 2115,
      "hr": 142,
      "pace": null,
      "cad": null,
      "stride": null
    },
    {
      "t": 2143,
      "hr": 128,
      "pace": null,
      "cad": null,
      "stride": null
    },
    {
      "t": 2167,
      "hr": 144,
      "pace": null,
      "cad": null,
      "stride": null
    },
    {
      "t": 2197,
      "hr": 139,
      "pace": null,
      "cad": null,
      "stride": null
    },
    {
      "t": 2223,
      "hr": 159,
      "pace": null,
      "cad": null,
      "stride": null
    },
    {
      "t": 2251,
      "hr": 165,
      "pace": null,
      "cad": null,
      "stride": null
    },
    {
      "t": 2275,
      "hr": 153,
      "pace": null,
      "cad": null,
      "stride": null
    },
    {
      "t": 2305,
      "hr": 138,
      "pace": null,
      "cad": null,
      "stride": null
    },
    {
      "t": 2336,
      "hr": 134,
      "pace": null,
      "cad": null,
      "stride": null
    },
    {
      "t": 2357,
      "hr": 151,
      "pace": null,
      "cad": null,
      "stride": null
    },
    {
      "t": 2370,
      "hr": 151,
      "pace": null,
      "cad": null,
      "stride": null
    },
    {
      "t": 2395,
      "hr": 138,
      "pace": null,
      "cad": null,
      "stride": null
    },
    {
      "t": 2424,
      "hr": 143,
      "pace": null,
      "cad": null,
      "stride": null
    },
    {
      "t": 2449,
      "hr": 146,
      "pace": null,
      "cad": null,
      "stride": null
    },
    {
      "t": 2469,
      "hr": 149,
      "pace": null,
      "cad": null,
      "stride": null
    }
  ],
  "splits": [
    {
      "n": 1,
      "distance_m": null,
      "duration_s": 2469.5,
      "pace_sec": null,
      "avg_hr": 133.0,
      "max_hr": 167.0,
      "elev_gain": null,
      "avg_cadence": null
    }
  ],
  "hr_zones": [
    {
      "zone": 1,
      "secs": 58.999,
      "low": 92
    },
    {
      "zone": 2,
      "secs": 268.001,
      "low": 110
    },
    {
      "zone": 3,
      "secs": 1632.001,
      "low": 128
    },
    {
      "zone": 4,
      "secs": 357.326,
      "low": 146
    },
    {
      "zone": 5,
      "secs": 12.998,
      "low": 152
    }
  ],
  "weather": {
    "temp_c": null,
    "feels_c": null,
    "humidity": null,
    "desc": null
  }
}
